dc_notifications/__init__.py
dc_notifications/discord_notifications.py
dc_notifications/smtp_connector.py
dc_notifications-1.0.2.dist-info/METADATA
dc_notifications-1.0.2.dist-info/WHEEL
dc_notifications-1.0.2.dist-info/top_level.txt
dc_notifications-1.0.2.dist-info/RECORD
