Metadata-Version: 2.1
Name: dc-notifications
Version: 1.0.2
Summary: Datareader Notifications
Home-page: UNKNOWN
Author: Calyx
License: UNKNOWN
Platform: UNKNOWN
